{
  "url": "https://www.essentialcardano.io/video/djed-vs-ust-or-lgc-review",
  "content": "# Djed vs UST | LGC Review\n\n![](https://lh3.googleusercontent.com/a-/AOh14Ggx9dJTUcJCBi2xxZdlFF9uBKWZxv-zg_bPnKlY=s96-c)\n\nIn the aftermath of the crash of the Luna ecosystem, knowledge is power. IF the Djed is a superior stablecoin, we will have to understand if it can withstand the tests that beat UST AND how the Djed does things differently.\n\n## 1 contributors\n\n![](https://lh3.googleusercontent.com/a-/AOh14Ggx9dJTUcJCBi2xxZdlFF9uBKWZxv-zg_bPnKlY=s96-c)\n\n## Would you like to suggest changes to this video?\n\nWe encourage you to actively participate in the creation and moderation of our content—your contributions are invaluable. All content is reviewed by another community member.\n\n##### Resources\n\n##### Legal\n\n##### Subscribe to our newsletter",
  "images": [],
  "extraction_metadata": {
    "batch_number": 47,
    "extraction_timestamp": "2025-09-19T10:05:31.431702",
    "extraction_time": 1.4371731281280518,
    "source": "tavily_api_raw"
  }
}