{
  "url": "https://www.essentialcardano.io/video/lace-a-lightwallet-platform",
  "content": "# Lace: a lightwallet platform\n\n![](https://ucarecdn.com/4f580f1c-e076-45b2-8a8d-af75d20c0cfd/)\n\nInput Output Global CEO Charles Hoskinson introduces Lace, a new lightwallet platform for speed, simplicity, and seamless flow. Now in development, Lace will help drive adoption by offering enhanced capability and ease of use to crypto users.\n\n## 1 contributors\n\n![](https://ucarecdn.com/4f580f1c-e076-45b2-8a8d-af75d20c0cfd/)\n\n## Would you like to suggest changes to this video?\n\nWe encourage you to actively participate in the creation and moderation of our content—your contributions are invaluable. All content is reviewed by another community member.\n\n##### Resources\n\n##### Legal\n\n##### Subscribe to our newsletter",
  "images": [],
  "extraction_metadata": {
    "batch_number": 49,
    "extraction_timestamp": "2025-09-19T10:05:41.121083",
    "extraction_time": 1.2582128047943115,
    "source": "tavily_api_raw"
  }
}